example_package_le/__init__.py
example_package_le/main.py
Example_Package_LE-0.5.0.dist-info/LICENSE
Example_Package_LE-0.5.0.dist-info/METADATA
Example_Package_LE-0.5.0.dist-info/WHEEL
Example_Package_LE-0.5.0.dist-info/top_level.txt
Example_Package_LE-0.5.0.dist-info/RECORD
